Metadata-Version: 2.1
Name: twzr
Version: 0.1.7
Summary: Tweezer: teeny tiny tools for data processing
Home-page: https://github.com/aspencage/twzr
Download-URL: https://github.com/aspencage/twzr/archive/refs/tags/v0.1.7.tar.gz
Author: Aspen Cage
Author-email: aspenncage@gmail.com
License: MIT
Classifier: Development Status :: 4 - Beta
Classifier: License :: OSI Approved :: MIT License
Classifier: Programming Language :: Python :: 3
Classifier: Programming Language :: Python :: 3.10
License-File: LICENSE
